cimico/__init__.py
cimico/example.py
cimico/generatevid.py
cimico/main.py
cimico/outputjson.py
cimico/testsuite.py
cimico/writetojson.py
cimico-1.0.0.dist-info/LICENSE
cimico-1.0.0.dist-info/METADATA
cimico-1.0.0.dist-info/WHEEL
cimico-1.0.0.dist-info/top_level.txt
cimico-1.0.0.dist-info/RECORD
